easy_tg_bot/__init__.py
easy_tg_bot/admin.py
easy_tg_bot/app.py
easy_tg_bot/cli.py
easy_tg_bot/decorators.py
easy_tg_bot/error.py
easy_tg_bot/file_handler.py
easy_tg_bot/mail_users_conv.py
easy_tg_bot/manage_role_conv.py
easy_tg_bot/mylogging.py
easy_tg_bot/put_file_conv.py
easy_tg_bot/put_intro_video_conv.py
easy_tg_bot/roles.py
easy_tg_bot/send.py
easy_tg_bot/send_with_navigation.py
easy_tg_bot/settings.py
easy_tg_bot/srv.py
easy_tg_bot/start.py
easy_tg_bot/superadmin.py
easy_tg_bot/text_handler.py
easy_tg_bot/utils/context_logic.py
easy_tg_bot/utils/init_templates.py
easy_tg_bot/utils/templates/.dockerignore
easy_tg_bot/utils/templates/.env
easy_tg_bot/utils/templates/.gitignore
easy_tg_bot/utils/templates/deploy.yml
easy_tg_bot/utils/templates/docker-compose.yml
easy_tg_bot/utils/templates/Dockerfile
easy_tg_bot/utils/templates/main.py
easy_tg_bot/utils/templates/settings.py
easy_tg_bot/utils/templates/text.xlsx
easy_tg_bot/utils/utils.py
easy_tg_bot/validate_text_file.py
easy_tg_bot/video_handler.py
easy_tg_bot-0.3.3.dist-info/entry_points.txt
easy_tg_bot-0.3.3.dist-info/LICENSE
easy_tg_bot-0.3.3.dist-info/METADATA
easy_tg_bot-0.3.3.dist-info/WHEEL
easy_tg_bot-0.3.3.dist-info/RECORD
